{
  "ComponentIndexes": {
    "Header": 18
  },
  "ControlUniqueIds": {
    "===below are non active screens===": 29,
    "ActiveGallery": 147,
    "ActiveGallery_1": 652,
    "Activegrp": 125,
    "Activegrp_1": 642,
    "ActiveWRContainer": 142,
    "ActiveWRContainer_1": 644,
    "ActiveWRHeader": 144,
    "ActiveWRHeader_1": 646,
    "ActiveWRSlicer": 143,
    "ActiveWRSlicer_1": 645,
    "adapt_details_1": 920,
    "adapt_details_2": 205,
    "adapt_details_3": 384,
    "adapt_details_4": 484,
    "App": 1,
    "as_businessLine": 701,
    "as_businessLine_1": 285,
    "as_businessLine_2": 276,
    "as_courseNameEN": 730,
    "as_courseNameEN_1": 308,
    "as_courseNameFR": 731,
    "as_courseNameFR_1": 309,
    "as_medium_10": 894,
    "as_medium_11": 271,
    "as_medium_2": 703,
    "as_medium_3": 906,
    "as_medium_4": 58,
    "as_medium_5": 552,
    "as_medium_6": 188,
    "as_medium_7": 368,
    "as_medium_8": 467,
    "as_medium_9": 904,
    "as_sdd_classID_3": 932,
    "as_sdd_classID_4": 72,
    "as_sdd_classID_5": 570,
    "as_sdd_classID_6": 216,
    "as_sdd_classID_7": 395,
    "as_sdd_classID_8": 494,
    "as_sdd_courseID_3": 925,
    "as_sdd_courseID_4": 66,
    "as_sdd_courseID_5": 564,
    "as_sdd_courseID_6": 210,
    "as_sdd_courseID_7": 389,
    "as_sdd_courseID_8": 488,
    "as_slnc_classID_10": 943,
    "as_slnc_classID_3": 933,
    "as_slnc_classID_4": 73,
    "as_slnc_classID_5": 571,
    "as_slnc_classID_6": 217,
    "as_slnc_classID_7": 396,
    "as_slnc_classID_8": 495,
    "as_slnc_classID_9": 941,
    "as_slnc_contentTitle_3": 946,
    "as_slnc_contentTitle_4": 83,
    "as_slnc_contentTitle_5": 581,
    "as_slnc_contentTitle_6": 227,
    "as_slnc_contentTitle_7": 407,
    "as_slnc_contentTitle_8": 506,
    "as_slnc_contentTitle_9": 929,
    "as_slnc_courseID_3": 926,
    "as_slnc_courseID_4": 67,
    "as_slnc_courseID_5": 565,
    "as_slnc_courseID_6": 211,
    "as_slnc_courseID_7": 390,
    "as_slnc_courseID_8": 489,
    "as_slnc_IntlFR_3": 948,
    "as_slnc_IntlFR_4": 87,
    "as_slnc_IntlFR_5": 585,
    "as_slnc_IntlFR_6": 230,
    "as_slnc_IntlFR_7": 411,
    "as_slnc_IntlFR_8": 510,
    "as_typeofWork": 699,
    "as_typeofWork_1": 283,
    "as_typeofWork_2": 689,
    "as_typeofWork_3": 688,
    "AttachmentControl_1": 93,
    "back": 648,
    "BackgroundBanner": 4,
    "backup": 30,
    "Body1": 782,
    "Body1_1": 834,
    "BodyContainer": 114,
    "BodyContainer_1": 626,
    "BodySlicer": 115,
    "BodySlicer_1": 627,
    "btn_Clear_10": 338,
    "btn_Clear_2": 760,
    "btn_Clear_3": 964,
    "btn_Clear_4": 106,
    "btn_Clear_5": 601,
    "btn_Clear_6": 246,
    "btn_Clear_7": 424,
    "btn_Clear_8": 965,
    "btn_Clear_9": 523,
    "btn_feedback_14": 17,
    "btn_feedback_15": 15,
    "btn_feedback_16": 18,
    "btn_feedback_17": 16,
    "btn_feedback_18": 613,
    "btn_feedback_19": 614,
    "btn_feedback_20": 615,
    "btn_feedback_21": 616,
    "btn_feedback_3": 39,
    "btn_feedback_4": 533,
    "btn_newWR": 118,
    "btn_newWR_1": 630,
    "btn_Submit_1": 664,
    "btn_Submit_10": 339,
    "btn_Submit_11": 434,
    "btn_Submit_12": 435,
    "btn_Submit_2": 666,
    "btn_Submit_3": 761,
    "btn_Submit_4": 966,
    "btn_Submit_5": 107,
    "btn_Submit_6": 602,
    "btn_Submit_7": 28,
    "btn_Submit_8": 247,
    "btn_Submit_9": 665,
    "btn_takeWR": 119,
    "btn_takeWR_1": 631,
    "btn_WR_Status_5": 40,
    "btn_WR_Status_6": 534,
    "Button1": 426,
    "Button2": 805,
    "Button2_1": 806,
    "Button2_2": 864,
    "Button2_3": 865,
    "Button3": 813,
    "Button3_1": 872,
    "Button4": 814,
    "Button4_1": 873,
    "Canvas2_1": 680,
    "Canvas2_2": 881,
    "Canvas2_3": 31,
    "Canvas2_4": 525,
    "Canvas2_5": 166,
    "Canvas2_6": 347,
    "Canvas2_7": 446,
    "Canvas2_8": 257,
    "cb_isaccessibility": 708,
    "cb_isaccessibility_1": 555,
    "cb_isaccessibility_3": 190,
    "cb_isaccessibility_4": 370,
    "cb_isaccessibility_5": 469,
    "cb_isaccessibility_6": 286,
    "cb_isadhoc": 723,
    "cb_isadhoc_2": 198,
    "cb_isadhoc_3": 378,
    "cb_isadhoc_4": 477,
    "cb_isadhoc_5": 301,
    "cb_isgnwt": 711,
    "cb_isgnwt_1": 554,
    "cb_isgnwt_3": 192,
    "cb_isgnwt_4": 372,
    "cb_isgnwt_5": 471,
    "cb_isgnwt_6": 288,
    "Checkbox1": 784,
    "Checkbox1_1": 836,
    "checkboxes": 724,
    "checkboxes_1": 302,
    "Closedgrp_1": 643,
    "Col1Title_1": 727,
    "Col1Title_10": 912,
    "Col1Title_11": 199,
    "Col1Title_12": 379,
    "Col1Title_13": 478,
    "Col1Title_14": 305,
    "Col1Title_2": 923,
    "Col1Title_3": 64,
    "Col1Title_4": 562,
    "Col1Title_5": 208,
    "Col1Title_6": 387,
    "Col1Title_7": 486,
    "Col1Title_8": 716,
    "Col1Title_9": 290,
    "Col2Title_2": 924,
    "Col2Title_3": 65,
    "Col2Title_4": 563,
    "Col2Title_5": 209,
    "Col2Title_6": 388,
    "Col2Title_7": 487,
    "CollegeBanner_9": 607,
    "Container1": 790,
    "Container1_1": 621,
    "Container1_2": 842,
    "Container1_3": 14,
    "Container1_4": 623,
    "Container10": 791,
    "Container10_1": 843,
    "Container11": 792,
    "Container11_1": 844,
    "Container12": 795,
    "Container12_1": 854,
    "Container12_2": 847,
    "Container12_3": 850,
    "Container13": 803,
    "Container13_1": 862,
    "Container14": 804,
    "Container14_1": 863,
    "Container15": 774,
    "Container15_1": 827,
    "Container16": 776,
    "Container16_1": 828,
    "Container19": 715,
    "Container19_1": 289,
    "Container2": 12,
    "Container2_1": 8,
    "Container2_2": 610,
    "Container2_8": 443,
    "Container20": 973,
    "Container3": 771,
    "Container3_1": 676,
    "Container3_2": 252,
    "Container3_3": 34,
    "Container3_4": 824,
    "Container4": 770,
    "Container4_1": 682,
    "Container4_10": 823,
    "Container4_2": 884,
    "Container4_3": 41,
    "Container4_4": 535,
    "Container4_5": 169,
    "Container4_6": 350,
    "Container4_7": 449,
    "Container4_8": 260,
    "Container4_9": 612,
    "Container5": 660,
    "Container5_3": 38,
    "Container5_4": 532,
    "Container5_8": 430,
    "Container6": 659,
    "Container6_1": 429,
    "Container7": 658,
    "Container7_1": 428,
    "Container8": 772,
    "Container8_1": 825,
    "Container9": 773,
    "Container9_1": 826,
    "content": 769,
    "content_1": 822,
    "DataCard2_1": 681,
    "DataCard2_2": 882,
    "DataCard2_3": 32,
    "DataCard2_4": 526,
    "DataCard2_5": 167,
    "DataCard2_6": 348,
    "DataCard2_7": 447,
    "DataCard2_8": 258,
    "dateP_dueDate_2": 691,
    "dateP_dueDate_4": 56,
    "dateP_dueDate_5": 550,
    "dateP_dueDate_6": 186,
    "dateP_dueDate_7": 366,
    "dateP_dueDate_8": 465,
    "dateP_dueDate_9": 268,
    "dateP_submitted_2": 693,
    "dateP_submitted_4": 47,
    "dateP_submitted_5": 541,
    "dateP_submitted_6": 175,
    "dateP_submitted_7": 355,
    "dateP_submitted_8": 454,
    "dateP_submitted_9": 267,
    "dd_Bizline_2": 706,
    "dd_Bizline_3": 282,
    "dd_lan_selector": 113,
    "dd_lan_selector_1": 677,
    "dd_lan_selector_10": 819,
    "dd_lan_selector_2": 878,
    "dd_lan_selector_3": 253,
    "dd_lan_selector_4": 163,
    "dd_lan_selector_5": 344,
    "dd_lan_selector_6": 766,
    "dd_lan_selector_7": 671,
    "dd_lan_selector_8": 440,
    "dd_lan_selector_9": 625,
    "dd_medium_2": 695,
    "dd_medium_4": 55,
    "dd_medium_5": 549,
    "dd_medium_6": 185,
    "dd_medium_7": 365,
    "dd_medium_8": 464,
    "dd_medium_9": 273,
    "dd_projectstatus": 687,
    "dd_projectstatus_1": 895,
    "dd_projectstatus_2": 180,
    "dd_projectstatus_3": 357,
    "dd_projectstatus_4": 461,
    "dd_projectstatus_5": 266,
    "dd_requestLan_2": 696,
    "dd_requestLan_4": 50,
    "dd_requestLan_5": 544,
    "dd_requestLan_6": 178,
    "dd_requestLan_7": 359,
    "dd_requestLan_8": 457,
    "dd_requestLan_9": 274,
    "dd_requestor": 277,
    "dd_requestor_1": 697,
    "dd_typeofwork_2": 707,
    "dd_typeofwork_4": 45,
    "dd_typeofwork_5": 539,
    "dd_typeofwork_6": 173,
    "dd_typeofwork_7": 353,
    "dd_typeofwork_8": 452,
    "dd_typeofwork_9": 284,
    "Debug": 425,
    "dp_WP_Tab": 714,
    "dp_WP_Tab_2": 197,
    "dp_WP_Tab_3": 377,
    "dp_WP_Tab_4": 476,
    "dp_WP_Tab_5": 300,
    "Dropdown1_2": 557,
    "Dropdown1_4": 27,
    "EditScreen_adaptDetails": 915,
    "EditScreen_BusinessLine": 901,
    "EditScreen_coments": 955,
    "EditScreen_contenttitleEN": 947,
    "EditScreen_contenttitleFR": 950,
    "EditScreen_coursenameEN": 938,
    "EditScreen_coursenameFR": 939,
    "EditScreen_details": 954,
    "EditScreen_duedate": 903,
    "EditScreen_gnwtcheck": 911,
    "EditScreen_language": 897,
    "EditScreen_medium": 902,
    "EditScreen_prioritycheck": 907,
    "EditScreen_requestor": 898,
    "EditScreen_SDCID": 928,
    "EditScreen_SDSID": 937,
    "EditScreen_SLCID": 927,
    "EditScreen_SLSID": 935,
    "EditScreen_submitdate": 891,
    "EditScreen_worktype": 888,
    "editWR": 874,
    "editWR_1": 159,
    "faq": 603,
    "FR IDs": 757,
    "FR IDs_1": 335,
    "FullHeaderContainer_10": 111,
    "FullHeaderContainer_11": 250,
    "FullHeaderContainer_12": 817,
    "FullHeaderContainer_2": 342,
    "FullHeaderContainer_3": 161,
    "FullHeaderContainer_4": 876,
    "FullHeaderContainer_5": 674,
    "FullHeaderContainer_6": 764,
    "FullHeaderContainer_7": 669,
    "FullHeaderContainer_8": 438,
    "FullHeaderContainer_9": 605,
    "gallery_WR": 779,
    "gallery_WR_1": 831,
    "Gallery2": 798,
    "Gallery2_1": 857,
    "galleryTemplate1": 132,
    "galleryTemplate1_1": 148,
    "galleryTemplate1_3": 653,
    "galleryTemplate2": 780,
    "galleryTemplate2_1": 832,
    "galleryTemplate3": 799,
    "galleryTemplate3_1": 858,
    "Group1": 956,
    "Group1_1": 238,
    "Group1_2": 417,
    "Group1_3": 516,
    "Group11": 756,
    "Group11_1": 334,
    "Group12": 754,
    "Group12_1": 332,
    "Group13": 755,
    "Group13_1": 333,
    "Group5": 158,
    "Group7": 722,
    "Group7_1": 296,
    "Group8": 667,
    "Group8_1": 436,
    "grp_file_uploads": 103,
    "grp_request_details_3": 96,
    "grp_request_details_4": 592,
    "grp_request_details_5": 237,
    "grp_request_details_6": 416,
    "grp_request_details_7": 515,
    "Header": 3,
    "Header_1": 528,
    "Header_10": 437,
    "Header_11": 249,
    "Header_12": 442,
    "Header_5": 673,
    "Header_6": 875,
    "Header_7": 160,
    "Header_8": 341,
    "Header_9": 668,
    "Header_Left_1": 6,
    "Header_Left_9": 609,
    "Header_Right_1": 11,
    "Header_Right_9": 617,
    "HeaderBackground_9": 606,
    "header-create": 675,
    "header-create_1": 251,
    "header-edit": 877,
    "header-edit-1": 162,
    "header-portal": 112,
    "header-reassign": 765,
    "header-reassign_1": 818,
    "Header-right-BG_9": 618,
    "Header-Right-items_9": 620,
    "HeaderSlicer_1": 5,
    "HeaderSlicer_9": 608,
    "header-submit-1": 670,
    "header-submit-2": 439,
    "header-view": 343,
    "Icon_search": 778,
    "Icon_search_1": 830,
    "Icon1_12": 345,
    "Icon1_14": 445,
    "Icon1_15": 164,
    "Icon1_16": 879,
    "Icon1_17": 678,
    "Icon1_18": 767,
    "Icon1_19": 649,
    "Icon1_20": 254,
    "Icon1_21": 820,
    "Icon2": 136,
    "Icon2_1": 152,
    "Icon3": 809,
    "Icon3_1": 868,
    "iconCheck1": 661,
    "iconCheck1_1": 431,
    "iconCircle1": 662,
    "iconCircle1_1": 432,
    "Image1_3": 35,
    "Image1_4": 529,
    "Image2_1": 622,
    "img_BannerDecoration_1": 7,
    "img_BannerDecoration_9": 619,
    "invisble": 385,
    "Label1": 709,
    "Label1_1": 686,
    "Label1_10": 460,
    "Label1_100": 88,
    "Label1_101": 90,
    "Label1_102": 540,
    "Label1_103": 542,
    "Label1_104": 543,
    "Label1_105": 546,
    "Label1_106": 547,
    "Label1_107": 551,
    "Label1_108": 553,
    "Label1_109": 568,
    "Label1_110": 569,
    "Label1_111": 572,
    "Label1_112": 574,
    "Label1_113": 578,
    "Label1_114": 579,
    "Label1_115": 583,
    "Label1_116": 586,
    "Label1_117": 588,
    "Label1_118": 174,
    "Label1_119": 176,
    "Label1_120": 177,
    "Label1_121": 181,
    "Label1_122": 183,
    "Label1_123": 187,
    "Label1_124": 189,
    "Label1_125": 214,
    "Label1_126": 215,
    "Label1_127": 218,
    "Label1_128": 220,
    "Label1_129": 224,
    "Label1_130": 225,
    "Label1_131": 228,
    "Label1_132": 231,
    "Label1_133": 233,
    "Label1_134": 354,
    "Label1_135": 356,
    "Label1_136": 358,
    "Label1_137": 362,
    "Label1_138": 363,
    "Label1_139": 367,
    "Label1_140": 369,
    "Label1_141": 393,
    "Label1_142": 394,
    "Label1_143": 397,
    "Label1_144": 399,
    "Label1_145": 402,
    "Label1_146": 404,
    "Label1_147": 409,
    "Label1_148": 413,
    "Label1_149": 414,
    "Label1_150": 453,
    "Label1_151": 455,
    "Label1_152": 456,
    "Label1_153": 459,
    "Label1_154": 462,
    "Label1_155": 466,
    "Label1_156": 742,
    "Label1_157": 740,
    "Label1_158": 738,
    "Label1_159": 739,
    "Label1_160": 468,
    "Label1_161": 492,
    "Label1_162": 493,
    "Label1_163": 496,
    "Label1_164": 498,
    "Label1_165": 501,
    "Label1_166": 503,
    "Label1_167": 508,
    "Label1_168": 512,
    "Label1_169": 513,
    "Label1_170": 712,
    "Label1_171": 278,
    "Label1_172": 280,
    "Label1_173": 914,
    "Label1_174": 744,
    "Label1_175": 746,
    "Label1_176": 200,
    "Label1_177": 196,
    "Label1_178": 194,
    "Label1_179": 374,
    "Label1_180": 375,
    "Label1_181": 380,
    "Label1_182": 473,
    "Label1_183": 474,
    "Label1_184": 479,
    "Label1_185": 717,
    "Label1_186": 721,
    "Label1_187": 281,
    "Label1_188": 291,
    "Label1_189": 293,
    "Label1_190": 295,
    "Label1_191": 298,
    "Label1_192": 310,
    "Label1_193": 311,
    "Label1_194": 316,
    "Label1_195": 317,
    "Label1_196": 318,
    "Label1_197": 320,
    "Label1_198": 322,
    "Label1_199": 324,
    "Label1_2": 556,
    "Label1_200": 327,
    "Label1_201": 329,
    "Label1_3": 265,
    "Label1_4": 26,
    "Label1_5": 287,
    "Label1_54": 705,
    "Label1_55": 692,
    "Label1_56": 694,
    "Label1_57": 700,
    "Label1_58": 704,
    "Label1_59": 698,
    "Label1_6": 892,
    "Label1_60": 690,
    "Label1_61": 269,
    "Label1_62": 270,
    "Label1_63": 272,
    "Label1_64": 275,
    "Label1_65": 732,
    "Label1_66": 733,
    "Label1_67": 749,
    "Label1_68": 751,
    "Label1_69": 719,
    "Label1_7": 182,
    "Label1_70": 889,
    "Label1_71": 890,
    "Label1_72": 896,
    "Label1_73": 899,
    "Label1_74": 900,
    "Label1_75": 905,
    "Label1_76": 893,
    "Label1_77": 930,
    "Label1_78": 931,
    "Label1_79": 934,
    "Label1_8": 360,
    "Label1_80": 936,
    "Label1_81": 940,
    "Label1_82": 942,
    "Label1_83": 945,
    "Label1_84": 949,
    "Label1_85": 951,
    "Label1_86": 46,
    "Label1_87": 48,
    "Label1_88": 49,
    "Label1_89": 52,
    "Label1_9": 909,
    "Label1_90": 53,
    "Label1_91": 57,
    "Label1_92": 59,
    "Label1_93": 70,
    "Label1_94": 71,
    "Label1_95": 74,
    "Label1_96": 76,
    "Label1_97": 80,
    "Label1_98": 81,
    "Label1_99": 85,
    "Label10": 810,
    "Label10_1": 869,
    "Label11": 812,
    "Label11_1": 871,
    "Label12": 19,
    "Label13": 702,
    "Label13_1": 279,
    "Label15": 108,
    "Label2": 138,
    "Label2_11": 92,
    "Label2_13": 684,
    "Label2_14": 752,
    "Label2_15": 886,
    "Label2_16": 953,
    "Label2_17": 43,
    "Label2_18": 94,
    "Label2_19": 537,
    "Label2_20": 590,
    "Label2_21": 171,
    "Label2_22": 235,
    "Label2_23": 352,
    "Label2_24": 406,
    "Label2_25": 451,
    "Label2_26": 505,
    "Label2_27": 262,
    "Label2_28": 330,
    "Label2_29": 710,
    "Label2_31": 193,
    "Label2_32": 373,
    "Label2_33": 472,
    "Label2_34": 297,
    "Label3": 22,
    "Label4": 133,
    "Label4_1": 149,
    "Label5": 154,
    "Label5_5": 37,
    "Label5_6": 531,
    "Label6": 793,
    "Label6_1": 796,
    "Label6_2": 845,
    "Label6_3": 855,
    "Label6_4": 848,
    "Label6_5": 851,
    "Label7": 346,
    "Label7_1": 165,
    "Label7_2": 880,
    "Label7_3": 679,
    "Label7_4": 768,
    "Label7_5": 650,
    "Label7_6": 255,
    "Label7_7": 256,
    "Label7_8": 821,
    "Label8": 800,
    "Label8_1": 859,
    "Label8_4": 801,
    "Label8_5": 802,
    "Label8_6": 860,
    "Label8_7": 861,
    "Label9": 797,
    "Label9_1": 856,
    "Label9_2": 849,
    "Label9_3": 852,
    "Label9_4": 853,
    "lbl_ActiveGallery": 145,
    "lbl_ActiveGallery_1": 647,
    "lbl_ActiveStatLabel": 122,
    "lbl_ActiveStatLabel_1": 636,
    "lbl_ActiveStatNum": 123,
    "lbl_ActiveStatNum_1": 637,
    "lbl_answer": 655,
    "lbl_AppName_1": 9,
    "lbl_AppName_9": 611,
    "lbl_ClosedStatLabel_1": 638,
    "lbl_ClosedStatNum_1": 639,
    "lbl_coursename": 137,
    "lbl_coursename_1": 153,
    "lbl_MyWRStatLabel_1": 632,
    "lbl_MyWRStatNum_1": 633,
    "lbl_notefor_accessibility": 191,
    "lbl_notefor_accessibility_1": 371,
    "lbl_notefor_accessibility_2": 470,
    "lbl_PlannedGallery": 129,
    "lbl_PlannedStatLabel": 120,
    "lbl_PlannedStatLabel_1": 634,
    "lbl_PlannedStatNum": 121,
    "lbl_PlannedStatNum_1": 635,
    "lbl_question": 654,
    "lbl_specialchar_warning_2": 944,
    "lbl_specialchar_warning_3": 82,
    "lbl_specialchar_warning_4": 580,
    "lbl_specialchar_warning_5": 226,
    "lbl_specialchar_warning_6": 405,
    "lbl_specialchar_warning_7": 504,
    "lbl_Username_11": 10,
    "lbl_Username_12": 624,
    "lbl_warning_10": 600,
    "lbl_warning_11": 172,
    "lbl_warning_12": 245,
    "lbl_warning_13": 264,
    "lbl_warning_14": 337,
    "lbl_warning_3": 685,
    "lbl_warning_4": 759,
    "lbl_warning_5": 887,
    "lbl_warning_6": 963,
    "lbl_warning_7": 44,
    "lbl_warning_8": 105,
    "lbl_warning_9": 538,
    "LblAppName2_5": 36,
    "LblAppName2_6": 530,
    "LblSuccessMsg1": 663,
    "LblSuccessMsg1_1": 433,
    "logo_1": 13,
    "Main_2": 883,
    "Main_3": 33,
    "Main_4": 527,
    "Main_5": 168,
    "Main_6": 349,
    "Main_7": 448,
    "Main_8": 259,
    "MyWRgrp_1": 640,
    "newHome": 672,
    "newHome_1": 248,
    "newHome_backup": 524,
    "NextArrow2": 785,
    "NextArrow2_1": 837,
    "PatchNotes": 967,
    "pickAPerson": 846,
    "PlannedGallery": 131,
    "Plannedgrp": 124,
    "Plannedgrp_1": 641,
    "PlannedWRContainer": 126,
    "PlannedWRHeader": 128,
    "PlannedWRSlicer": 127,
    "popups": 807,
    "popups_1": 866,
    "rawr_blSelector": 775,
    "reAssignWR": 762,
    "reAssignWR_1": 815,
    "Rectangle1": 808,
    "Rectangle1_1": 811,
    "Rectangle1_2": 867,
    "Rectangle1_3": 870,
    "RefreshActive": 146,
    "RefreshPlanned": 130,
    "Row1_2": 958,
    "Row1_3": 99,
    "Row1_4": 595,
    "Row1_5": 240,
    "Row1_6": 419,
    "Row1_7": 518,
    "Row2_2": 959,
    "Row2_3": 100,
    "Row2_4": 596,
    "Row2_5": 241,
    "Row2_6": 420,
    "Row2_7": 519,
    "Row3_2": 961,
    "Row3_3": 102,
    "Row3_4": 598,
    "Row3_5": 243,
    "Row3_6": 422,
    "Row3_7": 521,
    "Row5_2": 957,
    "Row5_3": 98,
    "Row5_4": 594,
    "Row5_5": 239,
    "Row5_6": 418,
    "Row5_7": 517,
    "Row6_3": 97,
    "Row6_4": 593,
    "Row7_2": 960,
    "Row7_3": 101,
    "Row7_4": 597,
    "Row7_5": 242,
    "Row7_6": 421,
    "Row7_7": 520,
    "RowTop1_2": 917,
    "RowTop1_3": 60,
    "RowTop1_4": 558,
    "RowTop1_5": 202,
    "RowTop1_6": 382,
    "RowTop1_7": 481,
    "RowTop2_2": 918,
    "RowTop2_3": 61,
    "RowTop2_4": 559,
    "RowTop2_5": 203,
    "RowTop2_6": 383,
    "RowTop2_7": 482,
    "RowTop3_2": 919,
    "RowTop3_3": 62,
    "RowTop3_4": 560,
    "RowTop3_5": 204,
    "RowTop3_7": 483,
    "screen_complete": 657,
    "screen_complete_1": 427,
    "Screen3": 25,
    "ScreenSlicer": 110,
    "ScreenSlicer_1": 604,
    "ScreenSlicer_reassign": 763,
    "ScreenSlicer_reassign_1": 816,
    "sdd_classID_10": 321,
    "sdd_classID_4": 77,
    "sdd_classID_5": 575,
    "sdd_classID_6": 221,
    "sdd_classID_7": 400,
    "sdd_classID_8": 743,
    "sdd_classID_9": 499,
    "sdd_classID_FR": 747,
    "sdd_classID_FR_1": 325,
    "sdd_courseID_10": 315,
    "sdd_courseID_4": 69,
    "sdd_courseID_5": 567,
    "sdd_courseID_6": 213,
    "sdd_courseID_7": 392,
    "sdd_courseID_8": 737,
    "sdd_courseID_9": 491,
    "sd-title": 735,
    "sd-title_1": 313,
    "section1_1": 683,
    "section1_2": 885,
    "section1_3": 42,
    "section1_4": 536,
    "section1_5": 170,
    "section1_6": 351,
    "section1_7": 450,
    "section1_8": 261,
    "section2_1": 726,
    "section2_2": 922,
    "section2_3": 63,
    "section2_4": 561,
    "section2_5": 207,
    "section2_6": 386,
    "section2_7": 485,
    "section2_8": 304,
    "Separator2": 789,
    "Separator2_1": 841,
    "Separator3": 141,
    "Separator3_1": 157,
    "Separator3_3": 656,
    "slnc_classID_10": 319,
    "slnc_classID_4": 75,
    "slnc_classID_5": 573,
    "slnc_classID_6": 219,
    "slnc_classID_7": 398,
    "slnc_classID_8": 741,
    "slnc_classID_9": 497,
    "slnc_classID_FR": 745,
    "slnc_classID_FR_1": 323,
    "slnc_contentTitleEN_2": 748,
    "slnc_contentTitleEN_4": 86,
    "slnc_contentTitleEN_5": 584,
    "slnc_contentTitleEN_6": 229,
    "slnc_contentTitleEN_7": 408,
    "slnc_contentTitleEN_8": 507,
    "slnc_contentTitleEN_9": 326,
    "slnc_contentTitleFR_2": 750,
    "slnc_contentTitleFR_4": 84,
    "slnc_contentTitleFR_5": 582,
    "slnc_contentTitleFR_6": 232,
    "slnc_contentTitleFR_7": 412,
    "slnc_contentTitleFR_8": 511,
    "slnc_contentTitleFR_9": 328,
    "slnc_courseID_tf_3": 68,
    "slnc_courseID_tf_4": 566,
    "slnc_courseID_tf_5": 212,
    "slnc_courseID_tf_6": 391,
    "slnc_courseID_tf_7": 736,
    "slnc_courseID_tf_8": 490,
    "slnc_courseID_tf_9": 314,
    "slnc_courseNameEN_1": 729,
    "slnc_courseNameEN_3": 78,
    "slnc_courseNameEN_4": 576,
    "slnc_courseNameEN_5": 222,
    "slnc_courseNameEN_6": 403,
    "slnc_courseNameEN_7": 502,
    "slnc_courseNameEN_8": 307,
    "slnc_courseNameFR_1": 728,
    "slnc_courseNameFR_3": 79,
    "slnc_courseNameFR_4": 577,
    "slnc_courseNameFR_5": 223,
    "slnc_courseNameFR_6": 401,
    "slnc_courseNameFR_7": 500,
    "slnc_courseNameFR_8": 306,
    "slnc_intlTitle_4": 89,
    "slnc_intlTitle_5": 587,
    "slnc_scormID_3": 952,
    "slnc_scormID_4": 91,
    "slnc_scormID_5": 589,
    "slnc_scormID_6": 234,
    "slnc_scormID_7": 415,
    "slnc_scormID_8": 514,
    "sl-title": 734,
    "sl-title_1": 312,
    "Stats": 116,
    "Stats_1": 628,
    "StatSlicer": 117,
    "StatSlicer_1": 629,
    "Status_PatchNotes_content": 974,
    "Status_PatchNotes_title": 975,
    "submission_1": 758,
    "submission_2": 962,
    "submission_3": 104,
    "submission_4": 599,
    "submission_5": 244,
    "submission_6": 423,
    "submission_7": 522,
    "submission_8": 336,
    "Subtitle2": 783,
    "Subtitle2_1": 786,
    "Subtitle2_2": 787,
    "Subtitle2_3": 788,
    "Subtitle2_4": 835,
    "Subtitle2_5": 838,
    "Subtitle2_6": 839,
    "Subtitle2_7": 840,
    "Subtitle3": 139,
    "Subtitle3_1": 140,
    "Subtitle3_2": 155,
    "Subtitle3_3": 156,
    "TestHeaderComponent_1": 444,
    "testlblA": 23,
    "testlblB": 24,
    "textInput_Bizline_4": 54,
    "textInput_Bizline_5": 548,
    "textInput_Bizline_6": 184,
    "textInput_Bizline_7": 364,
    "textInput_Bizline_8": 463,
    "textInput_requestDetails_2": 753,
    "textInput_requestDetails_4": 95,
    "textInput_requestDetails_5": 591,
    "textInput_requestDetails_6": 236,
    "textInput_requestDetails_7": 410,
    "textInput_requestDetails_8": 509,
    "textInput_requestDetails_9": 331,
    "textInput_Requestor_4": 51,
    "textInput_Requestor_5": 545,
    "textInput_Requestor_6": 179,
    "textInput_Requestor_7": 361,
    "textInput_Requestor_8": 458,
    "textInput_Requestor_9": 263,
    "TextInput1": 794,
    "TextInput2": 651,
    "Title2": 781,
    "Title2_1": 833,
    "Title3": 134,
    "Title3_1": 150,
    "Title3_2": 135,
    "Title3_3": 151,
    "txtInput_adaptlink": 718,
    "txtInput_adaptlink_2": 201,
    "txtInput_adaptlink_3": 381,
    "txtInput_adaptlink_4": 480,
    "txtInput_adaptlink_5": 292,
    "txtInput_adaptlink_FR": 720,
    "txtInput_adaptlink_FR_1": 294,
    "txtinput_searchbox": 777,
    "txtinput_searchbox_1": 829,
    "txtinput_wp_row_number": 713,
    "txtinput_wp_row_number_2": 195,
    "txtinput_wp_row_number_3": 376,
    "txtinput_wp_row_number_4": 475,
    "txtinput_wp_row_number_5": 299,
    "viewWR": 340,
    "viewWR_newbanner": 441,
    "VincentTestPage": 20,
    "VTTestHeader": 21,
    "wp_details": 725,
    "wp_details_1": 303,
    "wp_details_2": 206,
    "wr_status": 109
  },
  "FunctionParamsInvariantScripts": {},
  "FunctionParamsInvariantScriptsOnInstances": {},
  "HeaderLastSavedDateTimeUTC": "07/18/2022 21:52:45",
  "IsLegacyComponentAllowGlobalScopeCase": false,
  "LocalConnectionIDReferences": {
    "0903e8bf-f406-40ff-9313-bd87778b4d6b": "\"/providers/microsoft.powerapps/apis/shared_sharepointonline/connections/shared-sharepointonl-7d8bb547-2e5c-4426-924e-f63f5866ffda\"",
    "0f748b89-d170-443d-b263-828a7e6d6fd8": "\"/providers/microsoft.powerapps/apis/shared_sendmail/connections/3057e8226ada4ed68815d1e2acf76c40\"",
    "0fe6309e-eaba-4f9f-bce8-fe9912d58747": "\"/providers/microsoft.powerapps/apis/shared_logicflows/connections/4c74035ae1a4440f8c3739f83e561e07-245f2d88c2fb2e4b\"",
    "16e72adb-12aa-43dd-a044-fa3fb3edb6af": "\"/providers/microsoft.powerapps/apis/shared_logicflows/connections/1039ffdf79974793b2ac965250521068\"",
    "29c11814-1e0c-4dfe-b672-cccc648bedfd": "\"/providers/microsoft.powerapps/apis/shared_sharepointonline/connections/e6a466d36946404498bfb3a0aa3f2296\"",
    "34171488-d34b-4621-8e5c-95d4d1ad6c53": "\"/providers/microsoft.powerapps/apis/shared_office365users/connections/6f7deec1ceb6409e97a9956de3e496b9\"",
    "3e0a4be0-c28e-4d2e-a53b-b0f87a67a4f8": "\"/providers/microsoft.powerapps/apis/shared_logicflows/connections/4392afeeab7c4a2e84175a23376807f3\"",
    "4595088a-7972-403a-a78c-ffb8c7ce0c9b": "\"/providers/microsoft.powerapps/apis/shared_approvals/connections/c4ea832df62643b2b45537ccc963d3b2\"",
    "6876b3ff-a3a1-4cca-a769-eb7c2e36707f": "\"/providers/microsoft.powerapps/apis/shared_logicflows/connections/af73d8b0ce48428d90998ea12cf4e999\"",
    "95b78bd4-27bb-44da-9f58-3b014dc882f1": "\"/providers/microsoft.powerapps/apis/shared_teams/connections/1a515937b7fc4259b0b12a6a8134deda\"",
    "98b4ffbe-5c82-4a78-9e36-237c1cf70c7e": "\"/providers/microsoft.powerapps/apis/shared_logicflows/connections/9a5f56299b354c4fbb94f9807e3cade8\"",
    "c09495be-41a9-4b59-aee1-db04467b9a55": "\"/providers/microsoft.powerapps/apis/shared_sharepointonline/connections/e6a466d36946404498bfb3a0aa3f2296\"",
    "e2b32c60-8078-4824-a600-e451d611ffc3": "\"/providers/microsoft.powerapps/apis/shared_logicflows/connections/d00ab0dd7b5d416895fe99fbc2aac5c0-245f2d88c2fb2e4b\"",
    "e8e72622-8b64-4ed1-8ee1-16eff26f2cd0": "\"/providers/microsoft.powerapps/apis/shared_logicflows/connections/bf9f3759851b48a4bc8e7d5444b648ce\""
  },
  "LocalDatabaseReferencesAsEmpty": false,
  "LocalResourceFileNames": {
    "Asset 1": "0001.png",
    "Asset 2": "0002.png",
    "Asset 3": "0003.png",
    "background": "0004.png",
    "csp-banner": "0005.png",
    "dmc": "0006.png",
    "GetGroupImage": "0007.png",
    "GreyBar": "0008.png",
    "left": "0009.png",
    "med": "0010.png",
    "MeD_logo_BILpx": "0011.png",
    "MeD_logo_EN_150px": "0012.png",
    "MeD_logo_EN_white": "0013.png",
    "MeD_logo_FR_150px": "0014.png",
    "MeD_logo_FR_EN": "0015.jpg",
    "MeD_logo_FR_white": "0016.png",
    "MicrosoftTeams-image (2)": "0017.png",
    "MicrosoftTeams-image (3)": "0018.png"
  },
  "LocalResourceRootPaths": {
    "Asset 1": "https://docserverpwaprodcca.blob.core.windows.net/03af79ff-dfc8-4edd-b2a6-1c5d8e2e4cf4-1/resource/Assets0Images00001.png?sv=2017-04-17&sr=b&sig=dG83SazFg0%2BufRWok2%2FB07qampgwc%2BxY%2Br4qUWflBE0%3D&spr=https&se=2022-07-19T16%3A22%3A02Z&sp=r",
    "Asset 2": "https://docserverpwaprodcca.blob.core.windows.net/03af79ff-dfc8-4edd-b2a6-1c5d8e2e4cf4-1/resource/Assets0Images00002.png?sv=2017-04-17&sr=b&sig=QgSy5jjJLr%2BGpQOTAMFf9Td%2FF47eg6zm1BJlCEWdROo%3D&spr=https&se=2022-07-19T16%3A22%3A02Z&sp=r",
    "Asset 3": "https://docserverpwaprodcca.blob.core.windows.net/03af79ff-dfc8-4edd-b2a6-1c5d8e2e4cf4-1/resource/Assets0Images00003.png?sv=2017-04-17&sr=b&sig=mxqQDoiq7y1dDWLkyUpb1Mc2c%2FjUneO3j7Z0R5t1EBg%3D&spr=https&se=2022-07-19T16%3A22%3A02Z&sp=r",
    "background": "https://docserverpwaprodcca.blob.core.windows.net/03af79ff-dfc8-4edd-b2a6-1c5d8e2e4cf4-1/resource/Assets0Images00004.png?sv=2017-04-17&sr=b&sig=85OtYcUj9YEPTCK8G1a0YrxVFsNQcJ%2FDLOw6LOiYHhk%3D&spr=https&se=2022-07-19T16%3A22%3A02Z&sp=r",
    "csp-banner": "https://docserverpwaprodcca.blob.core.windows.net/03af79ff-dfc8-4edd-b2a6-1c5d8e2e4cf4-1/resource/Assets0Images00005.png?sv=2017-04-17&sr=b&sig=mxBwGDUCfZO1Cl5yWq10QReg0XAvgcFSbVAI00RyThw%3D&spr=https&se=2022-07-19T16%3A22%3A02Z&sp=r",
    "dmc": "https://docserverpwaprodcca.blob.core.windows.net/03af79ff-dfc8-4edd-b2a6-1c5d8e2e4cf4-1/resource/Assets0Images00006.png?sv=2017-04-17&sr=b&sig=XRNSkzP%2FrrVPcJv1xvzSV%2BOdAyrs1%2FLGjPlNPWYgxjA%3D&spr=https&se=2022-07-19T16%3A22%3A02Z&sp=r",
    "GetGroupImage": "https://docserverpwaprodcca.blob.core.windows.net/03af79ff-dfc8-4edd-b2a6-1c5d8e2e4cf4-1/resource/Assets0Images00007.png?sv=2017-04-17&sr=b&sig=RC5mClG3fRZapDlrhTpQFAvaByjhhPC0k18S5Kwe7qc%3D&spr=https&se=2022-07-19T16%3A22%3A02Z&sp=r",
    "GreyBar": "https://docserverpwaprodcca.blob.core.windows.net/03af79ff-dfc8-4edd-b2a6-1c5d8e2e4cf4-1/resource/Assets0Images00008.png?sv=2017-04-17&sr=b&sig=dg6RBTcANtaAY%2FHYXR%2BHuOE7wefp%2FKOldvRAeKuyAYs%3D&spr=https&se=2022-07-19T16%3A22%3A02Z&sp=r",
    "left": "https://docserverpwaprodcca.blob.core.windows.net/03af79ff-dfc8-4edd-b2a6-1c5d8e2e4cf4-1/resource/Assets0Images00009.png?sv=2017-04-17&sr=b&sig=AJJ9wyKx2oQOiOPCjfHBwXXqugV6Ol2Em2Y%2F%2FL%2Bwxu4%3D&spr=https&se=2022-07-19T16%3A22%3A02Z&sp=r",
    "med": "https://docserverpwaprodcca.blob.core.windows.net/03af79ff-dfc8-4edd-b2a6-1c5d8e2e4cf4-1/resource/Assets0Images00010.png?sv=2017-04-17&sr=b&sig=x5nIeozi8RaMJoDBXsdckICPHFNE7DWXhNhHif5QOjQ%3D&spr=https&se=2022-07-19T16%3A22%3A02Z&sp=r",
    "MeD_logo_BILpx": "https://docserverpwaprodcca.blob.core.windows.net/03af79ff-dfc8-4edd-b2a6-1c5d8e2e4cf4-1/resource/Assets0Images00011.png?sv=2017-04-17&sr=b&sig=qBeql8FXVjnS93ljQ7CHmhvZnmu8ipTa6P3novyNiuA%3D&spr=https&se=2022-07-19T16%3A22%3A02Z&sp=r",
    "MeD_logo_EN_150px": "https://docserverpwaprodcca.blob.core.windows.net/03af79ff-dfc8-4edd-b2a6-1c5d8e2e4cf4-1/resource/Assets0Images00012.png?sv=2017-04-17&sr=b&sig=yd1%2Brzm5KiI4fTBwGAKoOZlQtr6E8PV%2BggSeO2CFS3o%3D&spr=https&se=2022-07-19T16%3A22%3A02Z&sp=r",
    "MeD_logo_EN_white": "https://docserverpwaprodcca.blob.core.windows.net/03af79ff-dfc8-4edd-b2a6-1c5d8e2e4cf4-1/resource/Assets0Images00013.png?sv=2017-04-17&sr=b&sig=Vuox2ASG%2FuB9XacfFZnudYpRxvzvq3AGdWmaBBtFBrc%3D&spr=https&se=2022-07-19T16%3A22%3A02Z&sp=r",
    "MeD_logo_FR_150px": "https://docserverpwaprodcca.blob.core.windows.net/03af79ff-dfc8-4edd-b2a6-1c5d8e2e4cf4-1/resource/Assets0Images00014.png?sv=2017-04-17&sr=b&sig=SoGxt0%2BVR%2B3WWDknAofVO0U4AxWzMPs0RzeWw1uQmrU%3D&spr=https&se=2022-07-19T16%3A22%3A02Z&sp=r",
    "MeD_logo_FR_EN": "https://docserverpwaprodcca.blob.core.windows.net/03af79ff-dfc8-4edd-b2a6-1c5d8e2e4cf4-1/resource/Assets0Images00015.jpg?sv=2017-04-17&sr=b&sig=xBbnLRhCdNimjaHDHDk9I8ULjKUBuToXEN6w1%2BoGDjs%3D&spr=https&se=2022-07-19T16%3A22%3A02Z&sp=r",
    "MeD_logo_FR_white": "https://docserverpwaprodcca.blob.core.windows.net/03af79ff-dfc8-4edd-b2a6-1c5d8e2e4cf4-1/resource/Assets0Images00016.png?sv=2017-04-17&sr=b&sig=oe1ZVA5bymrfnkiFRbTm6wQlXs9UzpN2v0taeboHTTU%3D&spr=https&se=2022-07-19T16%3A22%3A02Z&sp=r",
    "MicrosoftTeams-image (2)": "https://docserverpwaprodcca.blob.core.windows.net/03af79ff-dfc8-4edd-b2a6-1c5d8e2e4cf4-1/resource/Assets0Images00017.png?sv=2017-04-17&sr=b&sig=7tVl622UzIRYJuSNROst0aFB9e59k6eOuDy9Zjh7gi8%3D&spr=https&se=2022-07-19T16%3A22%3A02Z&sp=r",
    "MicrosoftTeams-image (3)": "https://docserverpwaprodcca.blob.core.windows.net/03af79ff-dfc8-4edd-b2a6-1c5d8e2e4cf4-1/resource/Assets0Images00018.png?sv=2017-04-17&sr=b&sig=F%2FUPD1TF02wxulqlbEtNPTqIvWa1lBZnCmIQalKJXvA%3D&spr=https&se=2022-07-19T16%3A22%3A02Z&sp=r"
  },
  "OldLogoFileName": "logo.jpg",
  "OrderComponentMetadata": {
    "45fb0e9bfeb7446e8453bf428c2f970c": 0
  },
  "OrderComponentTemplate": {
    "45fb0e9bfeb7446e8453bf428c2f970c": 0
  },
  "OrderDataSource": {
    "activeWRs": 26,
    "allWRs": 28,
    "ComboBoxSample": 8,
    "CSP-NewWR": 5,
    "CustomGallerySample": 9,
    "dataForm": 17,
    "DropDownSample": 10,
    "faqPack": 18,
    "formData": 19,
    "formDataEN": 20,
    "formDataFR": 21,
    "langPack": 22,
    "LangTranslation": 11,
    "MeD FAQ DB": 12,
    "MED-DMC-AddToWorkPlan": 7,
    "MED-DMC-InitialWRApproval": 6,
    "MeD-PRD-InitialWRApproval": 4,
    "MeD-PRD-NewWR2": 2,
    "MeD-PRD-SaveWR": 0,
    "MED-ToolPatchNotes": 16,
    "NotifyCSH-reassignWR": 3,
    "numWRCol": 23,
    "Office365Users": 1,
    "plannedWRs": 27,
    "ProjectStatus": 13,
    "RadioSample": 14,
    "SelectedItems": 24,
    "selectedUsers": 25,
    "wrtracking-production-version-001": 15
  },
  "OrderGroupControls": {
    "Activegrp": {
      "lbl_ActiveStatLabel": 0,
      "lbl_ActiveStatNum": 1
    },
    "Activegrp_1": {
      "lbl_ActiveStatLabel_1": 0,
      "lbl_ActiveStatNum_1": 1
    },
    "adapt_details_1": {
      "Col1Title_10": 0,
      "EditScreen_adaptDetails": 1,
      "Label1_173": 2
    },
    "adapt_details_2": {
      "Col1Title_11": 0,
      "Label1_176": 2,
      "txtInput_adaptlink_2": 1
    },
    "adapt_details_3": {
      "Col1Title_12": 0,
      "Label1_181": 2,
      "txtInput_adaptlink_3": 1
    },
    "adapt_details_4": {
      "Col1Title_13": 0,
      "Label1_184": 2,
      "txtInput_adaptlink_4": 1
    },
    "checkboxes": {
      "cb_isaccessibility": 0,
      "cb_isgnwt": 1,
      "Label1": 2
    },
    "checkboxes_1": {
      "cb_isaccessibility_6": 0,
      "cb_isgnwt_6": 1,
      "Label1_5": 2
    },
    "Closedgrp_1": {
      "lbl_ClosedStatLabel_1": 0,
      "lbl_ClosedStatNum_1": 1
    },
    "EditScreen_coments": {
      "EditScreen_details": 1,
      "Label2_16": 0
    },
    "FR IDs": {
      "Label1_174": 1,
      "Label1_175": 3,
      "sdd_classID_FR": 0,
      "slnc_classID_FR": 2
    },
    "FR IDs_1": {
      "Label1_198": 1,
      "Label1_199": 3,
      "sdd_classID_FR_1": 0,
      "slnc_classID_FR_1": 2
    },
    "Group1": {
      "as_slnc_IntlFR_3": 1,
      "EditScreen_contenttitleFR": 2,
      "Label1_84": 0
    },
    "Group1_1": {
      "as_slnc_IntlFR_6": 1,
      "Label1_132": 0,
      "slnc_contentTitleFR_6": 2
    },
    "Group1_2": {
      "as_slnc_IntlFR_7": 1,
      "Label1_148": 0,
      "slnc_contentTitleFR_7": 2
    },
    "Group1_3": {
      "as_slnc_IntlFR_8": 1,
      "Label1_168": 0,
      "slnc_contentTitleFR_8": 2
    },
    "Group11": {
      "as_courseNameEN": 4,
      "as_courseNameFR": 5,
      "Label1_65": 0,
      "Label1_66": 2,
      "slnc_courseNameEN_1": 1,
      "slnc_courseNameFR_1": 3
    },
    "Group11_1": {
      "as_courseNameEN_1": 4,
      "as_courseNameFR_1": 5,
      "Label1_192": 0,
      "Label1_193": 2,
      "slnc_courseNameEN_8": 1,
      "slnc_courseNameFR_8": 3
    },
    "Group12": {
      "Label1_156": 5,
      "Label1_157": 2,
      "Label1_158": 3,
      "Label1_159": 0,
      "sdd_classID_8": 1,
      "sdd_courseID_8": 7,
      "slnc_classID_8": 4,
      "slnc_courseID_tf_7": 6
    },
    "Group12_1": {
      "Label1_194": 3,
      "Label1_195": 0,
      "Label1_196": 2,
      "Label1_197": 5,
      "sdd_classID_10": 1,
      "sdd_courseID_10": 7,
      "slnc_classID_10": 4,
      "slnc_courseID_tf_9": 6
    },
    "Group13": {
      "Label1_67": 2,
      "Label1_68": 1,
      "slnc_contentTitleEN_2": 3,
      "slnc_contentTitleFR_2": 0
    },
    "Group13_1": {
      "Label1_200": 2,
      "Label1_201": 1,
      "slnc_contentTitleEN_9": 3,
      "slnc_contentTitleFR_9": 0
    },
    "Group5": {
      "Icon2_1": 0,
      "Label5": 1
    },
    "Group7": {
      "Label1_185": 1,
      "Label1_186": 2,
      "txtInput_adaptlink_FR": 0
    },
    "Group7_1": {
      "Label1_188": 1,
      "Label1_190": 2,
      "txtInput_adaptlink_FR_1": 0
    },
    "Group8": {
      "iconCheck1": 1,
      "iconCircle1": 0
    },
    "Group8_1": {
      "iconCheck1_1": 1,
      "iconCircle1_1": 0
    },
    "grp_file_uploads": {
      "AttachmentControl_1": 0,
      "Label2_11": 1
    },
    "grp_request_details_3": {
      "Label2_18": 0,
      "textInput_requestDetails_4": 1
    },
    "grp_request_details_4": {
      "Label2_20": 0,
      "textInput_requestDetails_5": 1
    },
    "grp_request_details_5": {
      "Label2_22": 0,
      "textInput_requestDetails_6": 1
    },
    "grp_request_details_6": {
      "Label2_24": 0,
      "textInput_requestDetails_7": 1
    },
    "grp_request_details_7": {
      "Label2_26": 0,
      "textInput_requestDetails_8": 1
    },
    "invisble": {
      "cb_isadhoc_3": 0,
      "dp_WP_Tab_3": 1,
      "Label1_179": 3,
      "Label1_180": 5,
      "Label2_32": 4,
      "txtinput_wp_row_number_3": 2
    },
    "MyWRgrp_1": {
      "lbl_MyWRStatLabel_1": 0,
      "lbl_MyWRStatNum_1": 1
    },
    "Plannedgrp": {
      "lbl_PlannedStatLabel": 0,
      "lbl_PlannedStatNum": 1
    },
    "Plannedgrp_1": {
      "lbl_PlannedStatLabel_1": 0,
      "lbl_PlannedStatNum_1": 1
    },
    "Row1_2": {
      "as_sdd_courseID_3": 3,
      "as_slnc_courseID_3": 2,
      "EditScreen_SDCID": 5,
      "EditScreen_SLCID": 4,
      "Label1_77": 1,
      "Label1_78": 0
    },
    "Row1_3": {
      "as_sdd_courseID_4": 3,
      "as_slnc_courseID_4": 2,
      "Label1_93": 1,
      "Label1_94": 0,
      "sdd_courseID_4": 5,
      "slnc_courseID_tf_3": 4
    },
    "Row1_4": {
      "as_sdd_courseID_5": 3,
      "as_slnc_courseID_5": 2,
      "Label1_109": 1,
      "Label1_110": 0,
      "sdd_courseID_5": 5,
      "slnc_courseID_tf_4": 4
    },
    "Row1_5": {
      "as_sdd_courseID_6": 3,
      "as_slnc_courseID_6": 2,
      "Label1_125": 1,
      "Label1_126": 0,
      "sdd_courseID_6": 5,
      "slnc_courseID_tf_5": 4
    },
    "Row1_6": {
      "as_sdd_courseID_7": 3,
      "as_slnc_courseID_7": 2,
      "Label1_141": 1,
      "Label1_142": 0,
      "sdd_courseID_7": 5,
      "slnc_courseID_tf_6": 4
    },
    "Row1_7": {
      "as_sdd_courseID_8": 3,
      "as_slnc_courseID_8": 2,
      "Label1_161": 1,
      "Label1_162": 0,
      "sdd_courseID_9": 5,
      "slnc_courseID_tf_8": 4
    },
    "Row2_2": {
      "as_sdd_classID_3": 5,
      "as_slnc_classID_3": 4,
      "EditScreen_SDSID": 0,
      "EditScreen_SLSID": 2,
      "Label1_79": 1,
      "Label1_80": 3
    },
    "Row2_3": {
      "as_sdd_classID_4": 5,
      "as_slnc_classID_4": 4,
      "Label1_95": 1,
      "Label1_96": 3,
      "sdd_classID_4": 0,
      "slnc_classID_4": 2
    },
    "Row2_4": {
      "as_sdd_classID_5": 5,
      "as_slnc_classID_5": 4,
      "Label1_111": 1,
      "Label1_112": 3,
      "sdd_classID_5": 0,
      "slnc_classID_5": 2
    },
    "Row2_5": {
      "as_sdd_classID_6": 5,
      "as_slnc_classID_6": 4,
      "Label1_127": 1,
      "Label1_128": 3,
      "sdd_classID_6": 0,
      "slnc_classID_6": 2
    },
    "Row2_6": {
      "as_sdd_classID_7": 5,
      "as_slnc_classID_7": 4,
      "Label1_143": 1,
      "Label1_144": 3,
      "sdd_classID_7": 0,
      "slnc_classID_7": 2
    },
    "Row2_7": {
      "as_sdd_classID_8": 5,
      "as_slnc_classID_8": 4,
      "Label1_163": 1,
      "Label1_164": 3,
      "sdd_classID_9": 0,
      "slnc_classID_9": 2
    },
    "Row3_2": {
      "EditScreen_coursenameEN": 2,
      "EditScreen_coursenameFR": 4,
      "Label1_81": 1,
      "Label1_82": 3,
      "lbl_specialchar_warning_2": 0
    },
    "Row3_3": {
      "Label1_97": 1,
      "Label1_98": 3,
      "lbl_specialchar_warning_3": 0,
      "slnc_courseNameEN_3": 2,
      "slnc_courseNameFR_3": 4
    },
    "Row3_4": {
      "Label1_113": 1,
      "Label1_114": 3,
      "lbl_specialchar_warning_4": 0,
      "slnc_courseNameEN_4": 2,
      "slnc_courseNameFR_4": 4
    },
    "Row3_5": {
      "Label1_129": 1,
      "Label1_130": 3,
      "lbl_specialchar_warning_5": 0,
      "slnc_courseNameEN_5": 2,
      "slnc_courseNameFR_5": 4
    },
    "Row3_6": {
      "Label1_145": 1,
      "Label1_146": 3,
      "lbl_specialchar_warning_6": 0,
      "slnc_courseNameEN_6": 2,
      "slnc_courseNameFR_6": 4
    },
    "Row3_7": {
      "Label1_165": 1,
      "Label1_166": 3,
      "lbl_specialchar_warning_7": 0,
      "slnc_courseNameEN_7": 2,
      "slnc_courseNameFR_7": 4
    },
    "Row5_2": {
      "as_slnc_contentTitle_3": 1,
      "EditScreen_contenttitleEN": 2,
      "Label1_83": 0
    },
    "Row5_3": {
      "as_slnc_contentTitle_4": 1,
      "Label1_99": 0,
      "slnc_contentTitleEN_4": 2,
      "slnc_contentTitleFR_4": 3
    },
    "Row5_4": {
      "as_slnc_contentTitle_5": 1,
      "Label1_115": 0,
      "slnc_contentTitleEN_5": 2,
      "slnc_contentTitleFR_5": 3
    },
    "Row5_5": {
      "as_slnc_contentTitle_6": 1,
      "Label1_131": 0,
      "slnc_contentTitleEN_6": 2
    },
    "Row5_6": {
      "as_slnc_contentTitle_7": 1,
      "Label1_147": 0,
      "slnc_contentTitleEN_7": 2
    },
    "Row5_7": {
      "as_slnc_contentTitle_8": 1,
      "Label1_167": 0,
      "slnc_contentTitleEN_8": 2
    },
    "Row6_3": {
      "as_slnc_IntlFR_4": 2,
      "Label1_100": 1,
      "slnc_intlTitle_4": 0
    },
    "Row6_4": {
      "as_slnc_IntlFR_5": 2,
      "Label1_116": 1,
      "slnc_intlTitle_5": 0
    },
    "Row7_2": {
      "Label1_85": 0,
      "slnc_scormID_3": 1
    },
    "Row7_3": {
      "Label1_101": 0,
      "slnc_scormID_4": 1
    },
    "Row7_4": {
      "Label1_117": 0,
      "slnc_scormID_5": 1
    },
    "Row7_5": {
      "Label1_133": 0,
      "slnc_scormID_6": 1
    },
    "Row7_6": {
      "Label1_149": 0,
      "slnc_scormID_7": 1
    },
    "Row7_7": {
      "Label1_169": 0,
      "slnc_scormID_8": 1
    },
    "RowTop1_2": {
      "EditScreen_submitdate": 2,
      "EditScreen_worktype": 3,
      "Label1_70": 0,
      "Label1_71": 1
    },
    "RowTop1_3": {
      "dateP_submitted_4": 2,
      "dd_typeofwork_4": 3,
      "Label1_86": 0,
      "Label1_87": 1
    },
    "RowTop1_4": {
      "dateP_submitted_5": 2,
      "dd_typeofwork_5": 3,
      "Label1_102": 0,
      "Label1_103": 1
    },
    "RowTop1_5": {
      "dateP_submitted_6": 2,
      "dd_typeofwork_6": 3,
      "Label1_118": 0,
      "Label1_119": 1
    },
    "RowTop1_6": {
      "dateP_submitted_7": 2,
      "dd_typeofwork_7": 3,
      "Label1_134": 0,
      "Label1_135": 1
    },
    "RowTop1_7": {
      "dateP_submitted_8": 2,
      "dd_typeofwork_8": 3,
      "Label1_150": 0,
      "Label1_151": 1
    },
    "RowTop2_2": {
      "EditScreen_language": 3,
      "EditScreen_requestor": 0,
      "Label1_72": 2,
      "Label1_73": 1
    },
    "RowTop2_3": {
      "dd_requestLan_4": 3,
      "Label1_88": 2,
      "Label1_89": 1,
      "textInput_Requestor_4": 0
    },
    "RowTop2_4": {
      "dd_requestLan_5": 3,
      "Label1_104": 2,
      "Label1_105": 1,
      "textInput_Requestor_5": 0
    },
    "RowTop2_5": {
      "dd_requestLan_6": 3,
      "Label1_120": 2,
      "Label1_121": 1,
      "textInput_Requestor_6": 0
    },
    "RowTop2_6": {
      "dd_requestLan_7": 3,
      "Label1_136": 2,
      "Label1_137": 1,
      "textInput_Requestor_7": 0
    },
    "RowTop2_7": {
      "dd_requestLan_8": 3,
      "Label1_152": 2,
      "Label1_153": 1,
      "textInput_Requestor_8": 0
    },
    "RowTop3_2": {
      "as_medium_3": 6,
      "EditScreen_BusinessLine": 3,
      "EditScreen_duedate": 2,
      "EditScreen_medium": 5,
      "Label1_74": 0,
      "Label1_75": 4,
      "Label1_76": 1
    },
    "RowTop3_3": {
      "as_medium_4": 6,
      "dateP_dueDate_4": 2,
      "dd_medium_4": 5,
      "Label1_90": 0,
      "Label1_91": 4,
      "Label1_92": 1,
      "textInput_Bizline_4": 3
    },
    "RowTop3_4": {
      "as_medium_5": 6,
      "dateP_dueDate_5": 2,
      "dd_medium_5": 5,
      "Label1_106": 0,
      "Label1_107": 4,
      "Label1_108": 1,
      "textInput_Bizline_5": 3
    },
    "RowTop3_5": {
      "as_medium_6": 6,
      "dateP_dueDate_6": 2,
      "dd_medium_6": 5,
      "Label1_122": 0,
      "Label1_123": 4,
      "Label1_124": 1,
      "textInput_Bizline_6": 3
    },
    "RowTop3_7": {
      "as_medium_8": 6,
      "dateP_dueDate_8": 2,
      "dd_medium_8": 5,
      "Label1_154": 0,
      "Label1_155": 4,
      "Label1_160": 1,
      "textInput_Bizline_8": 3
    },
    "wp_details": {
      "cb_isadhoc": 0,
      "dp_WP_Tab": 1,
      "Label1_170": 3,
      "Label2_29": 4,
      "txtinput_wp_row_number": 2
    },
    "wp_details_1": {
      "cb_isadhoc_5": 0,
      "dp_WP_Tab_5": 1,
      "Label1_191": 3,
      "Label2_34": 4,
      "txtinput_wp_row_number_5": 2
    },
    "wp_details_2": {
      "cb_isadhoc_2": 0,
      "dp_WP_Tab_2": 1,
      "Label1_177": 3,
      "Label1_178": 5,
      "Label2_31": 4,
      "txtinput_wp_row_number_2": 2
    }
  },
  "OrderPcfTemplate": {},
  "OrderTemplate": {},
  "OrderXMLTemplate": {
    "attachments": 9,
    "button": 3,
    "checkbox": 13,
    "circle": 14,
    "combobox": 8,
    "datepicker": 6,
    "dropdown": 4,
    "fluidGrid": 5,
    "gallery": 11,
    "groupContainer": 1,
    "icon": 10,
    "image": 0,
    "label": 2,
    "rectangle": 12,
    "text": 7
  },
  "PublishOrderIndices": {
    "===below are non active screens===": 18,
    "ActiveGallery": 41,
    "ActiveGallery_1": 677,
    "Activegrp": 17,
    "Activegrp_1": 659,
    "ActiveWRContainer": 36,
    "ActiveWRContainer_1": 669,
    "ActiveWRHeader": 38,
    "ActiveWRHeader_1": 671,
    "ActiveWRSlicer": 37,
    "ActiveWRSlicer_1": 670,
    "adapt_details_1": 181,
    "adapt_details_2": 494,
    "adapt_details_3": 271,
    "adapt_details_4": 691,
    "App": 0,
    "as_businessLine": 81,
    "as_businessLine_1": 430,
    "as_businessLine_2": 421,
    "as_courseNameEN": 111,
    "as_courseNameEN_1": 455,
    "as_courseNameFR": 112,
    "as_courseNameFR_1": 456,
    "as_medium_10": 163,
    "as_medium_11": 416,
    "as_medium_2": 83,
    "as_medium_3": 176,
    "as_medium_4": 798,
    "as_medium_5": 876,
    "as_medium_6": 516,
    "as_medium_7": 258,
    "as_medium_8": 711,
    "as_medium_9": 174,
    "as_sdd_classID_3": 196,
    "as_sdd_classID_4": 817,
    "as_sdd_classID_5": 898,
    "as_sdd_classID_6": 546,
    "as_sdd_classID_7": 285,
    "as_sdd_classID_8": 741,
    "as_sdd_courseID_3": 188,
    "as_sdd_courseID_4": 810,
    "as_sdd_courseID_5": 891,
    "as_sdd_courseID_6": 538,
    "as_sdd_courseID_7": 278,
    "as_sdd_courseID_8": 733,
    "as_slnc_classID_10": 208,
    "as_slnc_classID_3": 197,
    "as_slnc_classID_4": 818,
    "as_slnc_classID_5": 899,
    "as_slnc_classID_6": 547,
    "as_slnc_classID_7": 286,
    "as_slnc_classID_8": 742,
    "as_slnc_classID_9": 206,
    "as_slnc_contentTitle_3": 212,
    "as_slnc_contentTitle_4": 828,
    "as_slnc_contentTitle_5": 909,
    "as_slnc_contentTitle_6": 557,
    "as_slnc_contentTitle_7": 300,
    "as_slnc_contentTitle_8": 753,
    "as_slnc_contentTitle_9": 192,
    "as_slnc_courseID_3": 189,
    "as_slnc_courseID_4": 811,
    "as_slnc_courseID_5": 892,
    "as_slnc_courseID_6": 539,
    "as_slnc_courseID_7": 279,
    "as_slnc_courseID_8": 734,
    "as_slnc_IntlFR_3": 215,
    "as_slnc_IntlFR_4": 832,
    "as_slnc_IntlFR_5": 913,
    "as_slnc_IntlFR_6": 560,
    "as_slnc_IntlFR_7": 305,
    "as_slnc_IntlFR_8": 757,
    "as_typeofWork": 79,
    "as_typeofWork_1": 428,
    "as_typeofWork_2": 69,
    "as_typeofWork_3": 68,
    "AttachmentControl_1": 838,
    "back": 673,
    "BackgroundBanner": 928,
    "backup": 20,
    "Body1": 332,
    "Body1_1": 589,
    "BodyContainer": 8,
    "BodyContainer_1": 651,
    "BodySlicer": 9,
    "BodySlicer_1": 652,
    "btn_Clear_10": 481,
    "btn_Clear_2": 140,
    "btn_Clear_3": 226,
    "btn_Clear_4": 843,
    "btn_Clear_5": 922,
    "btn_Clear_6": 569,
    "btn_Clear_7": 312,
    "btn_Clear_8": 227,
    "btn_Clear_9": 763,
    "btn_feedback_14": 941,
    "btn_feedback_15": 939,
    "btn_feedback_16": 942,
    "btn_feedback_17": 940,
    "btn_feedback_18": 638,
    "btn_feedback_19": 639,
    "btn_feedback_20": 640,
    "btn_feedback_21": 641,
    "btn_feedback_3": 776,
    "btn_feedback_4": 854,
    "btn_newWR": 12,
    "btn_newWR_1": 655,
    "btn_Submit_1": 372,
    "btn_Submit_10": 482,
    "btn_Submit_11": 386,
    "btn_Submit_12": 387,
    "btn_Submit_2": 374,
    "btn_Submit_3": 141,
    "btn_Submit_4": 228,
    "btn_Submit_5": 844,
    "btn_Submit_6": 923,
    "btn_Submit_7": 926,
    "btn_Submit_8": 570,
    "btn_Submit_9": 373,
    "btn_takeWR": 13,
    "btn_takeWR_1": 656,
    "btn_WR_Status_5": 777,
    "btn_WR_Status_6": 855,
    "Button1": 927,
    "Button2": 355,
    "Button2_1": 356,
    "Button2_2": 619,
    "Button2_3": 620,
    "Button3": 363,
    "Button3_1": 627,
    "Button4": 364,
    "Button4_1": 628,
    "Canvas2_1": 60,
    "Canvas2_2": 148,
    "Canvas2_3": 768,
    "Canvas2_4": 846,
    "Canvas2_5": 489,
    "Canvas2_6": 235,
    "Canvas2_7": 686,
    "Canvas2_8": 400,
    "cb_isaccessibility": 88,
    "cb_isaccessibility_1": 879,
    "cb_isaccessibility_3": 518,
    "cb_isaccessibility_4": 260,
    "cb_isaccessibility_5": 713,
    "cb_isaccessibility_6": 431,
    "cb_isadhoc": 105,
    "cb_isadhoc_2": 526,
    "cb_isadhoc_3": 269,
    "cb_isadhoc_4": 721,
    "cb_isadhoc_5": 446,
    "cb_isgnwt": 93,
    "cb_isgnwt_1": 878,
    "cb_isgnwt_3": 520,
    "cb_isgnwt_4": 262,
    "cb_isgnwt_5": 715,
    "cb_isgnwt_6": 433,
    "Checkbox1": 334,
    "Checkbox1_1": 591,
    "checkboxes": 89,
    "checkboxes_1": 408,
    "Closedgrp_1": 660,
    "Col1Title_1": 107,
    "Col1Title_10": 180,
    "Col1Title_11": 527,
    "Col1Title_12": 270,
    "Col1Title_13": 722,
    "Col1Title_14": 448,
    "Col1Title_2": 185,
    "Col1Title_3": 803,
    "Col1Title_4": 884,
    "Col1Title_5": 532,
    "Col1Title_6": 275,
    "Col1Title_7": 727,
    "Col1Title_8": 98,
    "Col1Title_9": 435,
    "Col2Title_2": 186,
    "Col2Title_3": 804,
    "Col2Title_4": 885,
    "Col2Title_5": 533,
    "Col2Title_6": 276,
    "Col2Title_7": 728,
    "CollegeBanner_9": 632,
    "Container1": 340,
    "Container1_1": 646,
    "Container1_2": 597,
    "Container1_3": 938,
    "Container1_4": 648,
    "Container10": 341,
    "Container10_1": 598,
    "Container11": 342,
    "Container11_1": 599,
    "Container12": 345,
    "Container12_1": 609,
    "Container12_2": 602,
    "Container12_3": 605,
    "Container13": 353,
    "Container13_1": 617,
    "Container14": 354,
    "Container14_1": 618,
    "Container15": 324,
    "Container15_1": 582,
    "Container16": 325,
    "Container16_1": 583,
    "Container19": 97,
    "Container19_1": 434,
    "Container2": 936,
    "Container2_1": 932,
    "Container2_2": 635,
    "Container2_8": 683,
    "Container20": 1,
    "Container3": 321,
    "Container3_1": 56,
    "Container3_2": 395,
    "Container3_3": 771,
    "Container3_4": 579,
    "Container4": 320,
    "Container4_1": 62,
    "Container4_10": 578,
    "Container4_2": 151,
    "Container4_3": 778,
    "Container4_4": 856,
    "Container4_5": 492,
    "Container4_6": 238,
    "Container4_7": 689,
    "Container4_8": 403,
    "Container4_9": 637,
    "Container5": 367,
    "Container5_3": 775,
    "Container5_4": 853,
    "Container5_8": 381,
    "Container6": 366,
    "Container6_1": 380,
    "Container7": 365,
    "Container7_1": 379,
    "Container8": 322,
    "Container8_1": 580,
    "Container9": 323,
    "Container9_1": 581,
    "content": 319,
    "content_1": 577,
    "DataCard2_1": 61,
    "DataCard2_2": 149,
    "DataCard2_3": 769,
    "DataCard2_4": 847,
    "DataCard2_5": 490,
    "DataCard2_6": 236,
    "DataCard2_7": 687,
    "DataCard2_8": 401,
    "dateP_dueDate_2": 71,
    "dateP_dueDate_4": 796,
    "dateP_dueDate_5": 874,
    "dateP_dueDate_6": 514,
    "dateP_dueDate_7": 256,
    "dateP_dueDate_8": 709,
    "dateP_dueDate_9": 413,
    "dateP_submitted_2": 73,
    "dateP_submitted_4": 787,
    "dateP_submitted_5": 865,
    "dateP_submitted_6": 503,
    "dateP_submitted_7": 244,
    "dateP_submitted_8": 698,
    "dateP_submitted_9": 412,
    "dd_Bizline_2": 86,
    "dd_Bizline_3": 427,
    "dd_lan_selector": 7,
    "dd_lan_selector_1": 57,
    "dd_lan_selector_10": 574,
    "dd_lan_selector_2": 145,
    "dd_lan_selector_3": 396,
    "dd_lan_selector_4": 486,
    "dd_lan_selector_5": 232,
    "dd_lan_selector_6": 316,
    "dd_lan_selector_7": 378,
    "dd_lan_selector_8": 391,
    "dd_lan_selector_9": 650,
    "dd_medium_2": 75,
    "dd_medium_4": 795,
    "dd_medium_5": 873,
    "dd_medium_6": 513,
    "dd_medium_7": 255,
    "dd_medium_8": 708,
    "dd_medium_9": 418,
    "dd_projectstatus": 67,
    "dd_projectstatus_1": 164,
    "dd_projectstatus_2": 508,
    "dd_projectstatus_3": 246,
    "dd_projectstatus_4": 705,
    "dd_projectstatus_5": 411,
    "dd_requestLan_2": 76,
    "dd_requestLan_4": 790,
    "dd_requestLan_5": 868,
    "dd_requestLan_6": 506,
    "dd_requestLan_7": 249,
    "dd_requestLan_8": 701,
    "dd_requestLan_9": 419,
    "dd_requestor": 422,
    "dd_requestor_1": 77,
    "dd_typeofwork_2": 87,
    "dd_typeofwork_4": 785,
    "dd_typeofwork_5": 863,
    "dd_typeofwork_6": 501,
    "dd_typeofwork_7": 242,
    "dd_typeofwork_8": 696,
    "dd_typeofwork_9": 429,
    "Debug": 99,
    "dp_WP_Tab": 96,
    "dp_WP_Tab_2": 525,
    "dp_WP_Tab_3": 268,
    "dp_WP_Tab_4": 720,
    "dp_WP_Tab_5": 445,
    "Dropdown1_2": 881,
    "Dropdown1_4": 925,
    "EditScreen_adaptDetails": 183,
    "EditScreen_BusinessLine": 171,
    "EditScreen_coments": 222,
    "EditScreen_contenttitleEN": 213,
    "EditScreen_contenttitleFR": 217,
    "EditScreen_coursenameEN": 203,
    "EditScreen_coursenameFR": 204,
    "EditScreen_details": 223,
    "EditScreen_duedate": 173,
    "EditScreen_gnwtcheck": 179,
    "EditScreen_language": 167,
    "EditScreen_medium": 172,
    "EditScreen_prioritycheck": 177,
    "EditScreen_requestor": 168,
    "EditScreen_SDCID": 191,
    "EditScreen_SDSID": 201,
    "EditScreen_SLCID": 190,
    "EditScreen_SLSID": 199,
    "EditScreen_submitdate": 159,
    "EditScreen_worktype": 156,
    "editWR": 101,
    "editWR_1": 194,
    "faq": 283,
    "FR IDs": 127,
    "FR IDs_1": 449,
    "FullHeaderContainer_10": 5,
    "FullHeaderContainer_11": 393,
    "FullHeaderContainer_12": 572,
    "FullHeaderContainer_2": 230,
    "FullHeaderContainer_3": 484,
    "FullHeaderContainer_4": 143,
    "FullHeaderContainer_5": 54,
    "FullHeaderContainer_6": 314,
    "FullHeaderContainer_7": 376,
    "FullHeaderContainer_8": 389,
    "FullHeaderContainer_9": 630,
    "gallery_WR": 329,
    "gallery_WR_1": 586,
    "Gallery2": 348,
    "Gallery2_1": 612,
    "galleryTemplate1": 26,
    "galleryTemplate1_1": 42,
    "galleryTemplate1_3": 678,
    "galleryTemplate2": 330,
    "galleryTemplate2_1": 587,
    "galleryTemplate3": 349,
    "galleryTemplate3_1": 613,
    "Group1": 214,
    "Group1_1": 545,
    "Group1_2": 304,
    "Group1_3": 740,
    "Group11": 108,
    "Group11_1": 452,
    "Group12": 117,
    "Group12_1": 450,
    "Group13": 131,
    "Group13_1": 451,
    "Group5": 46,
    "Group7": 100,
    "Group7_1": 438,
    "Group8": 368,
    "Group8_1": 382,
    "grp_file_uploads": 801,
    "grp_request_details_3": 802,
    "grp_request_details_4": 883,
    "grp_request_details_5": 531,
    "grp_request_details_6": 298,
    "grp_request_details_7": 726,
    "Header": 1,
    "Header_1": 849,
    "Header_10": 388,
    "Header_11": 392,
    "Header_12": 682,
    "Header_5": 53,
    "Header_6": 142,
    "Header_7": 483,
    "Header_8": 229,
    "Header_9": 375,
    "Header_Left_1": 930,
    "Header_Left_9": 634,
    "Header_Right_1": 935,
    "Header_Right_9": 642,
    "HeaderBackground_9": 631,
    "header-create": 55,
    "header-create_1": 394,
    "header-edit": 144,
    "header-edit-1": 485,
    "header-portal": 6,
    "header-reassign": 315,
    "header-reassign_1": 573,
    "Header-right-BG_9": 643,
    "Header-Right-items_9": 645,
    "HeaderSlicer_1": 929,
    "HeaderSlicer_9": 633,
    "header-submit-1": 377,
    "header-submit-2": 390,
    "header-view": 231,
    "Icon_search": 327,
    "Icon_search_1": 585,
    "Icon1_12": 233,
    "Icon1_14": 685,
    "Icon1_15": 487,
    "Icon1_16": 146,
    "Icon1_17": 58,
    "Icon1_18": 317,
    "Icon1_19": 674,
    "Icon1_20": 397,
    "Icon1_21": 575,
    "Icon2": 30,
    "Icon2_1": 47,
    "Icon3": 359,
    "Icon3_1": 623,
    "iconCheck1": 369,
    "iconCheck1_1": 383,
    "iconCircle1": 370,
    "iconCircle1_1": 384,
    "Image1_3": 772,
    "Image1_4": 850,
    "Image2_1": 647,
    "img_BannerDecoration_1": 931,
    "img_BannerDecoration_9": 644,
    "invisble": 264,
    "Label1": 90,
    "Label1_1": 66,
    "Label1_10": 704,
    "Label1_100": 833,
    "Label1_101": 835,
    "Label1_102": 864,
    "Label1_103": 866,
    "Label1_104": 867,
    "Label1_105": 870,
    "Label1_106": 871,
    "Label1_107": 875,
    "Label1_108": 877,
    "Label1_109": 895,
    "Label1_110": 896,
    "Label1_111": 900,
    "Label1_112": 902,
    "Label1_113": 906,
    "Label1_114": 907,
    "Label1_115": 911,
    "Label1_116": 914,
    "Label1_117": 916,
    "Label1_118": 502,
    "Label1_119": 504,
    "Label1_120": 505,
    "Label1_121": 509,
    "Label1_122": 511,
    "Label1_123": 515,
    "Label1_124": 517,
    "Label1_125": 542,
    "Label1_126": 543,
    "Label1_127": 548,
    "Label1_128": 550,
    "Label1_129": 554,
    "Label1_130": 555,
    "Label1_131": 558,
    "Label1_132": 561,
    "Label1_133": 563,
    "Label1_134": 243,
    "Label1_135": 245,
    "Label1_136": 248,
    "Label1_137": 252,
    "Label1_138": 253,
    "Label1_139": 257,
    "Label1_140": 259,
    "Label1_141": 282,
    "Label1_142": 283,
    "Label1_143": 287,
    "Label1_144": 289,
    "Label1_145": 293,
    "Label1_146": 295,
    "Label1_147": 302,
    "Label1_148": 307,
    "Label1_149": 308,
    "Label1_150": 697,
    "Label1_151": 699,
    "Label1_152": 700,
    "Label1_153": 703,
    "Label1_154": 706,
    "Label1_155": 710,
    "Label1_156": 124,
    "Label1_157": 122,
    "Label1_158": 120,
    "Label1_159": 121,
    "Label1_160": 712,
    "Label1_161": 737,
    "Label1_162": 738,
    "Label1_163": 743,
    "Label1_164": 745,
    "Label1_165": 748,
    "Label1_166": 750,
    "Label1_167": 755,
    "Label1_168": 759,
    "Label1_169": 760,
    "Label1_170": 94,
    "Label1_171": 423,
    "Label1_172": 425,
    "Label1_173": 182,
    "Label1_174": 126,
    "Label1_175": 129,
    "Label1_176": 528,
    "Label1_177": 524,
    "Label1_178": 522,
    "Label1_179": 265,
    "Label1_180": 266,
    "Label1_181": 272,
    "Label1_182": 717,
    "Label1_183": 718,
    "Label1_184": 723,
    "Label1_185": 99,
    "Label1_186": 104,
    "Label1_187": 426,
    "Label1_188": 436,
    "Label1_189": 439,
    "Label1_190": 441,
    "Label1_191": 443,
    "Label1_192": 457,
    "Label1_193": 458,
    "Label1_194": 463,
    "Label1_195": 464,
    "Label1_196": 465,
    "Label1_197": 467,
    "Label1_198": 469,
    "Label1_199": 471,
    "Label1_2": 880,
    "Label1_200": 474,
    "Label1_201": 476,
    "Label1_3": 410,
    "Label1_4": 924,
    "Label1_5": 432,
    "Label1_54": 85,
    "Label1_55": 72,
    "Label1_56": 74,
    "Label1_57": 80,
    "Label1_58": 84,
    "Label1_59": 78,
    "Label1_6": 161,
    "Label1_60": 70,
    "Label1_61": 414,
    "Label1_62": 415,
    "Label1_63": 417,
    "Label1_64": 420,
    "Label1_65": 113,
    "Label1_66": 114,
    "Label1_67": 133,
    "Label1_68": 135,
    "Label1_69": 102,
    "Label1_7": 510,
    "Label1_70": 157,
    "Label1_71": 158,
    "Label1_72": 166,
    "Label1_73": 169,
    "Label1_74": 170,
    "Label1_75": 175,
    "Label1_76": 162,
    "Label1_77": 193,
    "Label1_78": 194,
    "Label1_79": 198,
    "Label1_8": 250,
    "Label1_80": 200,
    "Label1_81": 205,
    "Label1_82": 207,
    "Label1_83": 210,
    "Label1_84": 216,
    "Label1_85": 218,
    "Label1_86": 786,
    "Label1_87": 788,
    "Label1_88": 789,
    "Label1_89": 792,
    "Label1_9": 178,
    "Label1_90": 793,
    "Label1_91": 797,
    "Label1_92": 799,
    "Label1_93": 814,
    "Label1_94": 815,
    "Label1_95": 819,
    "Label1_96": 821,
    "Label1_97": 825,
    "Label1_98": 826,
    "Label1_99": 830,
    "Label10": 360,
    "Label10_1": 624,
    "Label11": 362,
    "Label11_1": 626,
    "Label12": 943,
    "Label13": 82,
    "Label13_1": 424,
    "Label15": 845,
    "Label2": 32,
    "Label2_11": 837,
    "Label2_13": 64,
    "Label2_14": 136,
    "Label2_15": 153,
    "Label2_16": 221,
    "Label2_17": 780,
    "Label2_18": 839,
    "Label2_19": 858,
    "Label2_20": 918,
    "Label2_21": 495,
    "Label2_22": 565,
    "Label2_23": 240,
    "Label2_24": 297,
    "Label2_25": 692,
    "Label2_26": 752,
    "Label2_27": 405,
    "Label2_28": 477,
    "Label2_29": 91,
    "Label2_31": 521,
    "Label2_32": 263,
    "Label2_33": 716,
    "Label2_34": 442,
    "Label3": 765,
    "Label4": 27,
    "Label4_1": 43,
    "Label5": 49,
    "Label5_5": 774,
    "Label5_6": 852,
    "Label6": 343,
    "Label6_1": 346,
    "Label6_2": 600,
    "Label6_3": 610,
    "Label6_4": 603,
    "Label6_5": 606,
    "Label7": 234,
    "Label7_1": 488,
    "Label7_2": 147,
    "Label7_3": 59,
    "Label7_4": 318,
    "Label7_5": 675,
    "Label7_6": 398,
    "Label7_7": 399,
    "Label7_8": 576,
    "Label8": 350,
    "Label8_1": 614,
    "Label8_4": 351,
    "Label8_5": 352,
    "Label8_6": 615,
    "Label8_7": 616,
    "Label9": 347,
    "Label9_1": 611,
    "Label9_2": 604,
    "Label9_3": 607,
    "Label9_4": 608,
    "lbl_ActiveGallery": 39,
    "lbl_ActiveGallery_1": 672,
    "lbl_ActiveStatLabel": 18,
    "lbl_ActiveStatLabel_1": 665,
    "lbl_ActiveStatNum": 19,
    "lbl_ActiveStatNum_1": 666,
    "lbl_answer": 680,
    "lbl_AppName_1": 933,
    "lbl_AppName_9": 636,
    "lbl_ClosedStatLabel_1": 667,
    "lbl_ClosedStatNum_1": 668,
    "lbl_coursename": 31,
    "lbl_coursename_1": 48,
    "lbl_MyWRStatLabel_1": 661,
    "lbl_MyWRStatNum_1": 662,
    "lbl_notefor_accessibility": 519,
    "lbl_notefor_accessibility_1": 261,
    "lbl_notefor_accessibility_2": 714,
    "lbl_PlannedGallery": 23,
    "lbl_PlannedStatLabel": 15,
    "lbl_PlannedStatLabel_1": 663,
    "lbl_PlannedStatNum": 16,
    "lbl_PlannedStatNum_1": 664,
    "lbl_question": 679,
    "lbl_specialchar_warning_2": 209,
    "lbl_specialchar_warning_3": 827,
    "lbl_specialchar_warning_4": 908,
    "lbl_specialchar_warning_5": 556,
    "lbl_specialchar_warning_6": 296,
    "lbl_specialchar_warning_7": 751,
    "lbl_Username_11": 934,
    "lbl_Username_12": 649,
    "lbl_warning_10": 921,
    "lbl_warning_11": 496,
    "lbl_warning_12": 568,
    "lbl_warning_13": 407,
    "lbl_warning_14": 480,
    "lbl_warning_3": 65,
    "lbl_warning_4": 139,
    "lbl_warning_5": 154,
    "lbl_warning_6": 225,
    "lbl_warning_7": 781,
    "lbl_warning_8": 842,
    "lbl_warning_9": 859,
    "LblAppName2_5": 773,
    "LblAppName2_6": 851,
    "LblSuccessMsg1": 371,
    "LblSuccessMsg1_1": 385,
    "logo_1": 937,
    "Main_2": 150,
    "Main_3": 770,
    "Main_4": 848,
    "Main_5": 491,
    "Main_6": 237,
    "Main_7": 688,
    "Main_8": 402,
    "MyWRgrp_1": 657,
    "newHome": 337,
    "newHome_1": 337,
    "newHome_backup": 423,
    "NextArrow2": 335,
    "NextArrow2_1": 592,
    "PatchNotes": 0,
    "pickAPerson": 601,
    "PlannedGallery": 25,
    "Plannedgrp": 14,
    "Plannedgrp_1": 658,
    "PlannedWRContainer": 20,
    "PlannedWRHeader": 22,
    "PlannedWRSlicer": 21,
    "popups": 357,
    "popups_1": 621,
    "rawr_blSelector": 328,
    "reAssignWR": 502,
    "reAssignWR_1": 502,
    "Rectangle1": 358,
    "Rectangle1_1": 361,
    "Rectangle1_2": 622,
    "Rectangle1_3": 625,
    "RefreshActive": 40,
    "RefreshPlanned": 24,
    "Row1_2": 187,
    "Row1_3": 807,
    "Row1_4": 888,
    "Row1_5": 535,
    "Row1_6": 277,
    "Row1_7": 730,
    "Row2_2": 195,
    "Row2_3": 808,
    "Row2_4": 889,
    "Row2_5": 536,
    "Row2_6": 284,
    "Row2_7": 731,
    "Row3_2": 202,
    "Row3_3": 816,
    "Row3_4": 897,
    "Row3_5": 544,
    "Row3_6": 291,
    "Row3_7": 739,
    "Row5_2": 211,
    "Row5_3": 806,
    "Row5_4": 887,
    "Row5_5": 534,
    "Row5_6": 299,
    "Row5_7": 729,
    "Row6_3": 805,
    "Row6_4": 886,
    "Row7_2": 219,
    "Row7_3": 809,
    "Row7_4": 890,
    "Row7_5": 537,
    "Row7_6": 309,
    "Row7_7": 732,
    "RowTop1_2": 155,
    "RowTop1_3": 782,
    "RowTop1_4": 860,
    "RowTop1_5": 497,
    "RowTop1_6": 241,
    "RowTop1_7": 693,
    "RowTop2_2": 165,
    "RowTop2_3": 783,
    "RowTop2_4": 861,
    "RowTop2_5": 498,
    "RowTop2_6": 247,
    "RowTop2_7": 694,
    "RowTop3_2": 160,
    "RowTop3_3": 784,
    "RowTop3_4": 862,
    "RowTop3_5": 499,
    "RowTop3_7": 695,
    "screen_complete": 558,
    "screen_complete_1": 573,
    "Screen3": 554,
    "ScreenSlicer": 4,
    "ScreenSlicer_1": 629,
    "ScreenSlicer_reassign": 313,
    "ScreenSlicer_reassign_1": 571,
    "sdd_classID_10": 468,
    "sdd_classID_4": 822,
    "sdd_classID_5": 903,
    "sdd_classID_6": 551,
    "sdd_classID_7": 290,
    "sdd_classID_8": 125,
    "sdd_classID_9": 746,
    "sdd_classID_FR": 130,
    "sdd_classID_FR_1": 472,
    "sdd_courseID_10": 462,
    "sdd_courseID_4": 813,
    "sdd_courseID_5": 894,
    "sdd_courseID_6": 541,
    "sdd_courseID_7": 281,
    "sdd_courseID_8": 119,
    "sdd_courseID_9": 736,
    "sd-title": 116,
    "sd-title_1": 460,
    "section1_1": 63,
    "section1_2": 152,
    "section1_3": 779,
    "section1_4": 857,
    "section1_5": 493,
    "section1_6": 239,
    "section1_7": 690,
    "section1_8": 404,
    "section2_1": 106,
    "section2_2": 184,
    "section2_3": 800,
    "section2_4": 882,
    "section2_5": 530,
    "section2_6": 274,
    "section2_7": 725,
    "section2_8": 447,
    "Separator2": 339,
    "Separator2_1": 596,
    "Separator3": 35,
    "Separator3_1": 52,
    "Separator3_3": 681,
    "slnc_classID_10": 466,
    "slnc_classID_4": 820,
    "slnc_classID_5": 901,
    "slnc_classID_6": 549,
    "slnc_classID_7": 288,
    "slnc_classID_8": 123,
    "slnc_classID_9": 744,
    "slnc_classID_FR": 128,
    "slnc_classID_FR_1": 470,
    "slnc_contentTitleEN_2": 132,
    "slnc_contentTitleEN_4": 831,
    "slnc_contentTitleEN_5": 912,
    "slnc_contentTitleEN_6": 559,
    "slnc_contentTitleEN_7": 301,
    "slnc_contentTitleEN_8": 754,
    "slnc_contentTitleEN_9": 473,
    "slnc_contentTitleFR_2": 134,
    "slnc_contentTitleFR_4": 829,
    "slnc_contentTitleFR_5": 910,
    "slnc_contentTitleFR_6": 562,
    "slnc_contentTitleFR_7": 306,
    "slnc_contentTitleFR_8": 758,
    "slnc_contentTitleFR_9": 475,
    "slnc_courseID_tf_3": 812,
    "slnc_courseID_tf_4": 893,
    "slnc_courseID_tf_5": 540,
    "slnc_courseID_tf_6": 280,
    "slnc_courseID_tf_7": 118,
    "slnc_courseID_tf_8": 735,
    "slnc_courseID_tf_9": 461,
    "slnc_courseNameEN_1": 110,
    "slnc_courseNameEN_3": 823,
    "slnc_courseNameEN_4": 904,
    "slnc_courseNameEN_5": 552,
    "slnc_courseNameEN_6": 294,
    "slnc_courseNameEN_7": 749,
    "slnc_courseNameEN_8": 454,
    "slnc_courseNameFR_1": 109,
    "slnc_courseNameFR_3": 824,
    "slnc_courseNameFR_4": 905,
    "slnc_courseNameFR_5": 553,
    "slnc_courseNameFR_6": 292,
    "slnc_courseNameFR_7": 747,
    "slnc_courseNameFR_8": 453,
    "slnc_intlTitle_4": 834,
    "slnc_intlTitle_5": 915,
    "slnc_scormID_3": 220,
    "slnc_scormID_4": 836,
    "slnc_scormID_5": 917,
    "slnc_scormID_6": 564,
    "slnc_scormID_7": 310,
    "slnc_scormID_8": 761,
    "sl-title": 115,
    "sl-title_1": 459,
    "Stats": 10,
    "Stats_1": 653,
    "StatSlicer": 11,
    "StatSlicer_1": 654,
    "Status_PatchNotes_content": 3,
    "Status_PatchNotes_title": 2,
    "submission_1": 138,
    "submission_2": 224,
    "submission_3": 841,
    "submission_4": 920,
    "submission_5": 567,
    "submission_6": 311,
    "submission_7": 762,
    "submission_8": 479,
    "Subtitle2": 333,
    "Subtitle2_1": 336,
    "Subtitle2_2": 337,
    "Subtitle2_3": 338,
    "Subtitle2_4": 590,
    "Subtitle2_5": 593,
    "Subtitle2_6": 594,
    "Subtitle2_7": 595,
    "Subtitle3": 33,
    "Subtitle3_1": 34,
    "Subtitle3_2": 50,
    "Subtitle3_3": 51,
    "TestHeaderComponent_1": 684,
    "testlblA": 766,
    "testlblB": 767,
    "textInput_Bizline_4": 794,
    "textInput_Bizline_5": 872,
    "textInput_Bizline_6": 512,
    "textInput_Bizline_7": 254,
    "textInput_Bizline_8": 707,
    "textInput_requestDetails_2": 137,
    "textInput_requestDetails_4": 840,
    "textInput_requestDetails_5": 919,
    "textInput_requestDetails_6": 566,
    "textInput_requestDetails_7": 303,
    "textInput_requestDetails_8": 756,
    "textInput_requestDetails_9": 478,
    "textInput_Requestor_4": 791,
    "textInput_Requestor_5": 869,
    "textInput_Requestor_6": 507,
    "textInput_Requestor_7": 251,
    "textInput_Requestor_8": 702,
    "textInput_Requestor_9": 406,
    "TextInput1": 344,
    "TextInput2": 676,
    "Title2": 331,
    "Title2_1": 588,
    "Title3": 28,
    "Title3_1": 44,
    "Title3_2": 29,
    "Title3_3": 45,
    "txtInput_adaptlink": 101,
    "txtInput_adaptlink_2": 529,
    "txtInput_adaptlink_3": 273,
    "txtInput_adaptlink_4": 724,
    "txtInput_adaptlink_5": 437,
    "txtInput_adaptlink_FR": 103,
    "txtInput_adaptlink_FR_1": 440,
    "txtinput_searchbox": 326,
    "txtinput_searchbox_1": 584,
    "txtinput_wp_row_number": 95,
    "txtinput_wp_row_number_2": 523,
    "txtinput_wp_row_number_3": 267,
    "txtinput_wp_row_number_4": 719,
    "txtinput_wp_row_number_5": 444,
    "viewWR": 587,
    "viewWR_newbanner": 672,
    "VincentTestPage": 755,
    "VTTestHeader": 764,
    "wp_details": 92,
    "wp_details_1": 409,
    "wp_details_2": 500,
    "wr_status": 758
  },
  "ResourcesJsonIndices": {
    "Image-Asset 1": 1,
    "Image-Asset 2": 2,
    "Image-Asset 3": 3,
    "Image-background": 4,
    "Image-csp-banner": 5,
    "Image-dmc": 6,
    "Image-GetGroupImage": 7,
    "Image-GreyBar": 8,
    "Image-left": 9,
    "Image-med": 10,
    "Image-MeD_logo_BILpx": 11,
    "Image-MeD_logo_EN_150px": 12,
    "Image-MeD_logo_EN_white": 13,
    "Image-MeD_logo_FR_150px": 14,
    "Image-MeD_logo_FR_EN": 15,
    "Image-MeD_logo_FR_white": 16,
    "Image-MicrosoftTeams-image (2)": 17,
    "Image-MicrosoftTeams-image (3)": 18,
    "Image-SampleImage": 0
  },
  "RuleScreenIdWithoutScreen": {},
  "TemplateVersions": {},
  "VolatileProperties": {
    "AnalysisLoadTime": 6.0871804,
    "ControlCount": {
      "45fb0e9bfeb7446e8453bf428c2f970c": 13,
      "attachments": 1,
      "button": 46,
      "checkbox": 22,
      "circle": 2,
      "combobox": 11,
      "dataCard": 8,
      "datepicker": 16,
      "dropdown": 50,
      "fluidGrid": 8,
      "gallery": 7,
      "galleryTemplate": 7,
      "group": 90,
      "groupContainer": 142,
      "icon": 21,
      "image": 8,
      "label": 379,
      "rectangle": 9,
      "screen": 18,
      "text": 109
    },
    "DeserializationLoadTime": 10.6480519,
    "ErrorCount": 290
  },
  "WasLocalDatabaseReferencesEmpty": true
}